concave_hull-0.0.9.dist-info/RECORD
concave_hull-0.0.9.dist-info/WHEEL
concave_hull-0.0.9.dist-info/METADATA
concave_hull-0.0.9.dist-info/licenses/LICENSE
concave_hull/_core.pyi
concave_hull/__init__.py
concave_hull/_core.cpython-38-darwin.so
